CHANGES.txt
CONTRIBUTORS.txt
MANIFEST.in
README.rst
setup.py
collective/__init__.py
collective.js.unslider.egg-info/PKG-INFO
collective.js.unslider.egg-info/SOURCES.txt
collective.js.unslider.egg-info/dependency_links.txt
collective.js.unslider.egg-info/entry_points.txt
collective.js.unslider.egg-info/namespace_packages.txt
collective.js.unslider.egg-info/not-zip-safe
collective.js.unslider.egg-info/requires.txt
collective.js.unslider.egg-info/top_level.txt
collective/js/__init__.py
collective/js/unslider/__init__.py
collective/js/unslider/configure.zcml
collective/js/unslider/profiles/default/cssregistry.xml
collective/js/unslider/profiles/default/jsregistry.xml
collective/js/unslider/profiles/default/metadata.xml
collective/js/unslider/resources/unslider.css
collective/js/unslider/resources/unslider.js
docs/LICENSE.GPL
docs/LICENSE.txt