Metadata-Version: 1.1
Name: collective.js.unslider
Version: 1.1.dev0
Summary: Unslider.js resource for Plone
Home-page: http://svn.plone.org/svn/collective/
Author: UNKNOWN
Author-email: UNKNOWN
License: gpl
Platform: UNKNOWN
Classifier: Programming Language :: Python
